multicfg/__init__.py
multicfg/config.py
multicfg-0.0.7.dist-info/LICENCE.TXT
multicfg-0.0.7.dist-info/METADATA
multicfg-0.0.7.dist-info/WHEEL
multicfg-0.0.7.dist-info/top_level.txt
multicfg-0.0.7.dist-info/RECORD
