Metadata-Version: 2.1
Name: multicfg
Version: 0.0.7
Summary: Python package to read config from different sources: config files, command line, ...
Author-email: pyAxolotl <abdellatifzied.saada@gmail.com>
Classifier: Programming Language :: Python :: 3
Classifier: License :: OSI Approved :: MIT License
Classifier: Operating System :: OS Independent
Requires-Python: >=3.7
License-File: LICENCE.TXT
